__init__.py
config.py
config_file.py
main.py
run.py
midi2osc-0.1.0.dist-info/METADATA
midi2osc-0.1.0.dist-info/WHEEL
midi2osc-0.1.0.dist-info/entry_points.txt
midi2osc-0.1.0.dist-info/top_level.txt
midi2osc-0.1.0.dist-info/RECORD
