Metadata-Version: 2.4
Name: midi2osc
Version: 0.1.0
Summary: Forward MIDI messages to OSC
Requires-Python: >=3.12
Requires-Dist: click>=8.1.8
Requires-Dist: mido[ports-rtmidi]>=1.3.3
Requires-Dist: pre-commit>=4.2.0
Requires-Dist: pydantic>=2.10.6
Requires-Dist: python-osc>=1.9.3
Requires-Dist: pyyaml>=6.0.2
